LICENSE
README.rst
setup.py
src/coderfly_scraper.egg-info/PKG-INFO
src/coderfly_scraper.egg-info/SOURCES.txt
src/coderfly_scraper.egg-info/dependency_links.txt
src/coderfly_scraper.egg-info/top_level.txt
src/scraper/__init__.py
src/scraper/items.py
src/scraper/downloadermiddlewares/__init__.py
src/scraper/downloadermiddlewares/cookies.py
src/scraper/downloadermiddlewares/rabbitmq.py
src/scraper/downloadermiddlewares/retry.py
src/scraper/pipelines/__init__.py
src/scraper/pipelines/elasticsearch.py
src/scraper/pipelines/mongodb.py
src/scraper/pipelines/mysql.py
src/scraper/scheduler/__init__.py
src/scraper/scheduler/rabbitmq/__init__.py
src/scraper/scheduler/rabbitmq/connection.py
src/scraper/scheduler/rabbitmq/defaults.py
src/scraper/scheduler/rabbitmq/picklecompat.py
src/scraper/scheduler/rabbitmq/queue.py
src/scraper/scheduler/rabbitmq/scheduler.py
src/scraper/scheduler/rabbitmq/spiders.py
src/scraper/scheduler/rabbitmq/utils.py
src/scraper/spidermiddlewares/__init__.py
src/scraper/spidermiddlewares/log.py