Metadata-Version: 1.2
Name: coderfly-scraper
Version: 0.1.33
Summary: scrapy utils include piplines, utils
Home-page: https://github.com/coder-fly
Author: coder-fly
Author-email: coderflying@163.com
License: MIT
Platform: UNKNOWN
Requires-Python: >=3.6
